MANIFEST.in
README.txt
setup.cfg
setup.py
collective/__init__.py
collective.imageinbox.egg-info/PKG-INFO
collective.imageinbox.egg-info/SOURCES.txt
collective.imageinbox.egg-info/dependency_links.txt
collective.imageinbox.egg-info/entry_points.txt
collective.imageinbox.egg-info/namespace_packages.txt
collective.imageinbox.egg-info/not-zip-safe
collective.imageinbox.egg-info/requires.txt
collective.imageinbox.egg-info/top_level.txt
collective/imageinbox/__init__.py
collective/imageinbox/configure.zcml
collective/imageinbox/tests.py
collective/imageinbox/browser/__init__.py
collective/imageinbox/browser/configure.zcml
collective/imageinbox/browser/js/collective.imageinbox.js
collective/imageinbox/profiles/default/jsregistry.xml
collective/imageinbox/profiles/default/metadata.xml
docs/HISTORY.txt
docs/INSTALL.txt
docs/LICENSE.GPL
docs/LICENSE.txt