Metadata-Version: 1.0
Name: collective.imageinbox
Version: 1.0
Summary: Displays scaled plone content images inside Thickbox.
Home-page: https://github.com/martinschoel/collective.imageinbox
Author: Vitaliy Podoba
Author-email: vitaliy@martinschoel.com
License: GPL
Keywords: plone image scales thickbox
Platform: UNKNOWN
Classifier: Framework :: Plone
Classifier: Programming Language :: Python
